[{"lastname": "NORCROSS", "congress_office": "1531 Longworth House Office Building", "comments": "", "facebook_id": "DonaldNorcrossNJ", "feccandid": "H4NJ01084", "bioguide_id": "N000188", "youtube_url": "", "exit_code": "0", "gender": "M", "website": "https://norcross.house.gov", "office": "NJ01", "webform": "http://norcross.house.gov/contact", "votesmart_id": "", "firstlast": "Don Norcross", "twitter_id": "DonaldNorcross", "first_elected": "2014", "phone": "202-225-6501", "party": "D", "fax": "202-225-6583", "birthdate": "1958-12-13", "cid": "N00036154"}, {"lastname": "LOBIONDO", "congress_office": "2427 Rayburn House Office Building", "comments": "Retiring at end of 115th", "facebook_id": "FrankLoBiondo", "feccandid": "H2NJ02037", "bioguide_id": "L000554", "youtube_url": "https://youtube.com/USRepFrankLoBiondo", "exit_code": "4", "gender": "M", "website": "http://lobiondo.house.gov", "office": "NJ02", "webform": "https://lobiondo.house.gov/contact-me/email-me", "votesmart_id": "21890", "firstlast": "Frank LoBiondo", "twitter_id": "RepLoBiondo", "first_elected": "1994", "phone": "202-225-6572", "party": "R", "fax": "202-225-3318", "birthdate": "1946-05-12", "cid": "N00000851"}, {"lastname": "MACARTHUR", "congress_office": "506 Cannon House Office Building", "comments": "", "facebook_id": "CongressmanTomMacArthur", "feccandid": "H4NJ03130", "bioguide_id": "M001193", "youtube_url": "", "exit_code": "0", "gender": "M", "website": "https://macarthur.house.gov", "office": "NJ03", "webform": "", "votesmart_id": "", "firstlast": "Thomas MacArthur", "twitter_id": "RepTomMacArthur", "first_elected": "2014", "phone": "202-225-4765", "party": "R", "fax": "202-225-0778", "birthdate": "1960-10-16", "cid": "N00036155"}, {"lastname": "SMITH", "congress_office": "2373 Rayburn House Office Building", "comments": "", "facebook_id": "RepChrisSmith", "feccandid": "H8NJ04014", "bioguide_id": "S000522", "youtube_url": "https://youtube.com/USRepChrisSmith", "exit_code": "0", "gender": "M", "website": "http://chrissmith.house.gov", "office": "NJ04", "webform": "https://chrissmith.house.gov/contact/write.htm", "votesmart_id": "26952", "firstlast": "Chris Smith", "twitter_id": "RepChrisSmith", "first_elected": "1980", "phone": "202-225-3765", "party": "R", "fax": "202-225-7768", "birthdate": "1953-03-04", "cid": "N00009816"}, {"lastname": "GOTTHEIMER", "congress_office": "213 Cannon House Office Building", "comments": "", "facebook_id": "RepJoshG", "feccandid": "", "bioguide_id": "G000583", "youtube_url": "", "exit_code": "0", "gender": "M", "website": "https://gottheimer.house.gov", "office": "NJ05", "webform": "", "votesmart_id": "", "firstlast": "Josh Gottheimer", "twitter_id": "RepJoshG", "first_elected": "2016", "phone": "202-225-4465", "party": "D", "fax": "", "birthdate": "1975-03-08", "cid": "N00036944"}, {"lastname": "PALLONE", "congress_office": "237 Cannon House Office Building", "comments": "", "facebook_id": "repfrankpallone", "feccandid": "H8NJ03073", "bioguide_id": "P000034", "youtube_url": "https://youtube.com/repfrankpallone", "exit_code": "0", "gender": "M", "website": "https://pallone.house.gov", "office": "NJ06", "webform": "https://pallone.house.gov/contact-me/email-me", "votesmart_id": "26951", "firstlast": "Frank Pallone Jr.", "twitter_id": "FrankPallone", "first_elected": "1988", "phone": "202-225-4671", "party": "D", "fax": "202-225-9665", "birthdate": "1951-10-30", "cid": "N00000781"}, {"lastname": "LANCE", "congress_office": "2352 Rayburn House Office Building", "comments": "", "facebook_id": "CongressmanLance", "feccandid": "H6NJ12136", "bioguide_id": "L000567", "youtube_url": "https://youtube.com/CongressmanLance", "exit_code": "0", "gender": "M", "website": "http://lance.house.gov", "office": "NJ07", "webform": "https://lance.house.gov/contact-me1", "votesmart_id": "4443", "firstlast": "Leonard Lance", "twitter_id": "RepLanceNJ7", "first_elected": "2008", "phone": "202-225-5361", "party": "R", "fax": "202-225-9460", "birthdate": "1952-06-25", "cid": "N00000898"}, {"lastname": "SIRES", "congress_office": "2342 Rayburn House Office Building", "comments": "", "facebook_id": "81058818750", "feccandid": "H6NJ13191", "bioguide_id": "S001165", "youtube_url": "https://youtube.com/RepSiresNJ13", "exit_code": "0", "gender": "M", "website": "https://sires.house.gov", "office": "NJ08", "webform": "https://sires.house.gov/contact-me/email-me", "votesmart_id": "22510", "firstlast": "Albio Sires", "twitter_id": "RepSires", "first_elected": "2006", "phone": "202-225-7919", "party": "D", "fax": "202-226-0792", "birthdate": "1951-01-26", "cid": "N00027523"}, {"lastname": "PASCRELL", "congress_office": "2370 Rayburn House Office Building", "comments": "", "facebook_id": "pascrell", "feccandid": "H6NJ08118", "bioguide_id": "P000096", "youtube_url": "https://youtube.com/RepPascrell", "exit_code": "0", "gender": "M", "website": "http://pascrell.house.gov", "office": "NJ09", "webform": "https://pascrell.house.gov/contact/email-me", "votesmart_id": "478", "firstlast": "Bill Pascrell Jr.", "twitter_id": "BillPascrell", "first_elected": "1996", "phone": "202-225-5751", "party": "D", "fax": "202-225-5782", "birthdate": "1937-01-25", "cid": "N00000751"}, {"lastname": "PAYNE", "congress_office": "132 Cannon House Office Building", "comments": "", "facebook_id": "DonaldPayneJr", "feccandid": "H2NJ10154", "bioguide_id": "P000604", "youtube_url": "", "exit_code": "0", "gender": "M", "website": "http://payne.house.gov", "office": "NJ10", "webform": "http://payne.house.gov/contact/email-me", "votesmart_id": "90668", "firstlast": "Donald M Payne Jr.", "twitter_id": "RepDonaldPayne", "first_elected": "2012", "phone": "202-225-3436", "party": "D", "fax": "202-225-4160", "birthdate": "1958-12-17", "cid": "N00034639"}, {"lastname": "FRELINGHUYSEN", "congress_office": "2306 Rayburn House Office Building", "comments": "", "facebook_id": "rfrelinghuysen", "feccandid": "H2NJ05014", "bioguide_id": "F000372", "youtube_url": "https://youtube.com/RepFrelinghuysen", "exit_code": "0", "gender": "M", "website": "https://frelinghuysen.house.gov", "office": "NJ11", "webform": "https://frelinghuysenforms.house.gov/contact-form", "votesmart_id": "22177", "firstlast": "Rodney Frelinghuysen", "twitter_id": "USRepRodney", "first_elected": "1994", "phone": "202-225-5034", "party": "R", "fax": "202-225-3186", "birthdate": "1946-04-29", "cid": "N00000684"}, {"lastname": "COLEMAN", "congress_office": "1535 Longworth House Office Building", "comments": "", "facebook_id": "RepBonnie", "feccandid": "H4NJ12149", "bioguide_id": "W000822", "youtube_url": "", "exit_code": "0", "gender": "F", "website": "https://watsoncoleman.house.gov", "office": "NJ12", "webform": "", "votesmart_id": "", "firstlast": "Bonnie Coleman", "twitter_id": "RepBonnie", "first_elected": "2014", "phone": "202-225-5801", "party": "D", "fax": "202-225-6025", "birthdate": "1945-02-06", "cid": "N00036158"}, {"lastname": "MENENDEZ", "congress_office": "528 Hart Senate Office Building", "comments": "", "facebook_id": "senatormenendez", "feccandid": "H2NJ13075", "bioguide_id": "M000639", "youtube_url": "https://youtube.com/SenatorMenendezNJ", "exit_code": "0", "gender": "M", "website": "https://www.menendez.senate.gov", "office": "NJS1", "webform": "https://www.menendez.senate.gov/contact", "votesmart_id": "26961", "firstlast": "Robert Menendez", "twitter_id": "SenatorMenendez", "first_elected": "2006", "phone": "202-224-4744", "party": "D", "fax": "202-228-2197", "birthdate": "1954-01-01", "cid": "N00000699"}, {"lastname": "BOOKER", "congress_office": "359 Dirksen Senate Office Building", "comments": "", "facebook_id": "", "feccandid": "S4NJ00185", "bioguide_id": "B001288", "youtube_url": "https://youtube.com/SenCoryBooker", "exit_code": "0", "gender": "M", "website": "https://www.booker.senate.gov", "office": "NJS2", "webform": "https://www.booker.senate.gov/?p=contact", "votesmart_id": "76151", "firstlast": "Cory Booker", "twitter_id": "CoryBooker", "first_elected": "2013", "phone": "202-224-3224", "party": "D", "fax": "202-224-8378", "birthdate": "1969-04-27", "cid": "N00035267"}]